{
  "Dataset": {
    "AtomTypeStyle": "chemicalsymbol",
    "Data": [
      {
        "AtomTypes": [
          "N",
          "N",
          "N",
          "N",
          "W",
          "W"
        ],
        "Charges": [
          -0.08799032411501237,
          -0.08799057457484426,
          -0.08799032411000275,
          -0.08799057457073975,
          0.17598089868503344,
          0.1759808986855657
        ],
        "Energy": -38.97840784,
        "Forces": [
          [
            0.0,
            0.0,
            0.000933
          ],
          [
            -0.0,
            -0.0,
            0.000933
          ],
          [
            -0.0,
            -0.0,
            -0.000933
          ],
          [
            0.0,
            0.0,
            -0.000933
          ],
          [
            -0.0,
            0.0,
            0.0
          ],
          [
            0.0,
            0.0,
            0.0
          ]
        ],
        "Lattice": [
          [
            2.590122028,
            -1.49540765,
            0.0
          ],
          [
            0.0,
            2.9908153,
            0.0
          ],
          [
            0.0,
            0.0,
            7.9512417
          ]
        ],
        "NumAtoms": 6,
        "Positions": [
          [
            0.0,
            0.0,
            0.72116
          ],
          [
            0.0,
            -0.0,
            4.69678
          ],
          [
            -0.0,
            -0.0,
            7.23008
          ],
          [
            -0.0,
            0.0,
            3.25446
          ],
          [
            1.72675,
            0.0,
            1.98781
          ],
          [
            0.86337,
            1.49541,
            5.96343
          ]
        ],
        "Stress": [
          [
            -178309.95,
            0.0,
            0.0
          ],
          [
            0.0,
            -178309.95,
            0.0
          ],
          [
            0.0,
            0.0,
            -252822.7
          ]
        ]
      }
    ],
    "EnergyStyle": "electronvolt",
    "ForcesStyle": "electronvoltperangstrom",
    "Label": null,
    "LatticeStyle": "angstrom",
    "PositionsStyle": "angstrom",
    "StressStyle": "bar"
  }
}