{
  "Dataset": {
    "AtomTypeStyle": "chemicalsymbol",
    "Data": [
      {
        "AtomTypes": [
          "W"
        ],
        "Charges": [
          -8.776127782784305e-18
        ],
        "Energy": -8.68009,
        "Forces": [
          [
            0.0,
            0.0,
            0.0
          ]
        ],
        "Lattice": [
          [
            3.066160396898667,
            0.0,
            0.0
          ],
          [
            0.07304762564382906,
            3.136426352327578,
            0.0
          ],
          [
            1.777521077335403,
            1.692112410736531,
            1.605353254033318
          ]
        ],
        "NumAtoms": 1,
        "Positions": [
          [
            0.0,
            0.0,
            0.0
          ]
        ],
        "Stress": [
          [
            222001,
            6977.68,
            -218640
          ],
          [
            6977.68,
            183110,
            -132437
          ],
          [
            -218640,
            -132437,
            141174
          ]
        ]
      }
    ],
    "EnergyStyle": "electronvolt",
    "ForcesStyle": "electronvoltperangstrom",
    "Label": "Cysani W 504 slice_sample 1",
    "LatticeStyle": "angstrom",
    "PositionsStyle": "angstrom",
    "StressStyle": "bar"
  }
}