{
  "Dataset": {
    "AtomTypeStyle": "chemicalsymbol",
    "Data": [
      {
        "AtomTypes": [
          "W",
          "W",
          "W",
          "W",
          "W",
          "W",
          "W",
          "W",
          "W",
          "W",
          "W",
          "W"
        ],
        "Charges": [
          0.0321921659710605,
          -0.04465807269890175,
          -0.05130612412911859,
          0.015536929646893186,
          0.027122246789111293,
          0.023800926717109348,
          0.015118998714772099,
          0.01490460841174506,
          -0.04862863148413559,
          0.039006453213577555,
          0.02814860113157301,
          -0.05123810228368604
        ],
        "Energy": -101.19,
        "Forces": [
          [
            -1.487853140157264,
            2.899239273914352,
            -1.02208823163432
          ],
          [
            -0.9494423519469549,
            -1.430071788784656,
            1.667810387953331
          ],
          [
            -1.275979204375821,
            2.688877650345038,
            2.086333973386929
          ],
          [
            -1.865849160145078,
            -1.88118589372259,
            -0.547521755236776
          ],
          [
            3.833538958192726,
            -1.535498159340089,
            -1.966645430506096
          ],
          [
            -3.696354574413072,
            0.737463215851746,
            1.235443683348097
          ],
          [
            -4.860626377367598,
            0.600730488671126,
            1.207403279550953
          ],
          [
            2.943826239569363,
            0.08400429677072986,
            -1.454220473039287
          ],
          [
            3.055355785137829,
            -3.951074138904235,
            -0.5952553286569999
          ],
          [
            1.055616937737536,
            -3.064757574421951,
            0.5784474142912975
          ],
          [
            0.7717396755867125,
            2.18434746348183,
            -0.2881481251489498
          ],
          [
            2.47602721218162,
            2.667925166138702,
            -0.9015593943081781
          ]
        ],
        "Lattice": [
          [
            13.49370914255528,
            0.4497903047518427,
            1.272199098293054
          ],
          [
            0.0,
            4.497903047518427,
            0.0
          ],
          [
            0.0,
            0.0,
            3.180497745732636
          ]
        ],
        "NumAtoms": 12,
        "Positions": [
          [
            0.1621215125258843,
            0.03934778304010102,
            0.1624204925489842
          ],
          [
            2.329788800004889,
            2.414180546525191,
            -0.03989432308232793
          ],
          [
            2.327784419850026,
            0.03910751302153721,
            1.539701048960876
          ],
          [
            0.1466661913317703,
            2.525723975143296,
            1.731674943793224
          ],
          [
            4.359517156826412,
            0.220195937012849,
            0.1766428836478391
          ],
          [
            6.866751100541124,
            2.125810634245062,
            -0.1467503113382695
          ],
          [
            6.936682225944165,
            -0.1823685340902161,
            1.436281540970445
          ],
          [
            4.395628649616469,
            2.37486964348794,
            1.725071213283005
          ],
          [
            8.872538045512878,
            0.01628404125814287,
            -0.05475038423014167
          ],
          [
            11.06778393512267,
            2.221148921611119,
            -0.08845247683404356
          ],
          [
            11.13354398020344,
            -0.3252315751281461,
            1.550365699784852
          ],
          [
            8.869739665296668,
            2.024640306428409,
            1.549182879693464
          ]
        ],
        "Stress": [
          [
            0,
            0,
            0
          ],
          [
            0,
            0,
            0
          ],
          [
            0,
            0,
            0
          ]
        ]
      }
    ],
    "EnergyStyle": "electronvolt",
    "ForcesStyle": "electronvoltperangstrom",
    "Label": "Cysani W 3937 gamma_surface 12",
    "LatticeStyle": "angstrom",
    "PositionsStyle": "angstrom",
    "StressStyle": "bar"
  }
}