{
  "Dataset": {
    "AtomTypeStyle": "chemicalsymbol",
    "Data": [
      {
        "AtomTypes": [
          "W",
          "W",
          "W",
          "W",
          "W",
          "W",
          "W",
          "W",
          "W",
          "W",
          "W",
          "W"
        ],
        "Charges": [
          -0.004518423215973752,
          -0.005844344069971255,
          0.0062972225548926525,
          -0.009874524387116832,
          0.007890917299973297,
          0.0176298251725251,
          -0.01761726829810319,
          -0.023115621829948425,
          -0.0014978297473279478,
          0.016769088985766456,
          0.015289884187946922,
          -0.0014089266526632906
        ],
        "Energy": -100.215,
        "Forces": [
          [
            -0.1430679642954843,
            -4.57287548807837,
            -2.877273233665828
          ],
          [
            0.1160991979678428,
            -3.237867575034036,
            1.61247748777711
          ],
          [
            0.503981408800473,
            3.584580199012356,
            1.488226597420862
          ],
          [
            0.5355306243743903,
            4.190596035116243,
            -2.181531501730733
          ],
          [
            0.05633907084741949,
            4.672447997110293,
            -1.141836807949729
          ],
          [
            -3.041805957143035,
            4.703818243533356,
            1.795048809022452
          ],
          [
            -1.968323904204897,
            -4.386467314520731,
            2.147533027965803
          ],
          [
            0.3729849281736062,
            -4.758003266635017,
            -1.070057275561008
          ],
          [
            3.376694065184675,
            -1.586441766817082,
            -1.592283887412483
          ],
          [
            -2.048732448038348,
            -4.361972010774189,
            2.490503251674346
          ],
          [
            -1.046151219149901,
            4.132496662625253,
            1.510830954126116
          ],
          [
            3.286452197483259,
            1.619688284461921,
            -2.181637421666908
          ]
        ],
        "Lattice": [
          [
            13.49370914255528,
            4.048112742766584,
            0.3180497745732636
          ],
          [
            0.0,
            4.497903047518427,
            0.0
          ],
          [
            0.0,
            0.0,
            3.180497745732636
          ]
        ],
        "NumAtoms": 12,
        "Positions": [
          [
            0.02997068231560447,
            0.4174655622543579,
            0.2094296861810235
          ],
          [
            2.265259915019238,
            2.461126390152335,
            -0.1973712852493635
          ],
          [
            2.260356554640393,
            -0.09828534759375385,
            1.391919417542924
          ],
          [
            0.004625660357389253,
            2.277469555962582,
            1.766051716449254
          ],
          [
            4.562414372502722,
            -0.1993640454033285,
            0.04235686327258956
          ],
          [
            6.838212188336142,
            2.012319495476473,
            -0.1244636996163543
          ],
          [
            6.778471823720463,
            0.08619102665931888,
            1.439876041248164
          ],
          [
            4.529308199944862,
            2.430431647780789,
            1.636410956432907
          ],
          [
            8.84845723365234,
            -0.05549206428744524,
            0.1394489807741519
          ],
          [
            11.27352176101845,
            2.354304361899018,
            -0.07422212573457365
          ],
          [
            11.2010652654203,
            -0.2861557421090564,
            1.549481259716518
          ],
          [
            8.876882005848504,
            2.093698341763993,
            1.762575396180665
          ]
        ],
        "Stress": [
          [
            0,
            0,
            0
          ],
          [
            0,
            0,
            0
          ],
          [
            0,
            0,
            0
          ]
        ]
      }
    ],
    "EnergyStyle": "electronvolt",
    "ForcesStyle": "electronvoltperangstrom",
    "Label": "Cysani W 4681 gamma_surface 12",
    "LatticeStyle": "angstrom",
    "PositionsStyle": "angstrom",
    "StressStyle": "bar"
  }
}