{
  "Dataset": {
    "AtomTypeStyle": "chemicalsymbol",
    "Data": [
      {
        "AtomTypes": [
          "W",
          "W",
          "W",
          "W",
          "W",
          "W",
          "W",
          "W",
          "W",
          "W",
          "W",
          "W"
        ],
        "Charges": [
          0.02963518785756853,
          0.005130491674414812,
          -0.013831196701285915,
          0.012317443984508021,
          -0.023800304744418802,
          -0.004599808485813688,
          0.00032094748594852125,
          -0.021889996876743884,
          0.008968416424069281,
          -0.014445630502376242,
          0.0014636382844802284,
          0.020730811599649224
        ],
        "Energy": -98.895,
        "Forces": [
          [
            -3.234256927548855,
            1.389678813852667,
            2.626797742924604
          ],
          [
            0.9061307757376911,
            -0.3628144672184812,
            1.695813838488439
          ],
          [
            2.275081752603208,
            1.538426556203777,
            -5.155349451531248
          ],
          [
            -0.05377846972734455,
            -0.1908048837843975,
            0.01322292859495242
          ],
          [
            -0.6554683849134234,
            -1.79718885938654,
            -0.2504795696302779
          ],
          [
            -0.7316725975705227,
            0.06162161733196914,
            2.340815343004893
          ],
          [
            0.5534592837360361,
            0.07584792934103887,
            -2.904274696510411
          ],
          [
            0.7761201152148058,
            -0.4584493399254815,
            0.5551160089399946
          ],
          [
            1.180230125794194,
            0.0863861406964806,
            3.12038360286941
          ],
          [
            -2.519804699698497,
            -0.9506016278136122,
            4.168789995930749
          ],
          [
            -1.800629352083872,
            0.1496557302232043,
            -2.96605015367341
          ],
          [
            3.304588378456579,
            0.4582423904793759,
            -3.244785589407695
          ]
        ],
        "Lattice": [
          [
            15.58119319383914,
            1.652635107686423,
            2.248951523759213
          ],
          [
            0.0,
            2.754391842810706,
            0.0
          ],
          [
            0.0,
            0.0,
            4.497903047518427
          ]
        ],
        "NumAtoms": 12,
        "Positions": [
          [
            0.18624136438944,
            -0.9894428064466474,
            -0.8701437772293273
          ],
          [
            5.176658869960677,
            0.8432768351535254,
            -0.1529683818186921
          ],
          [
            2.566976708330577,
            1.411565409060819,
            0.1560554420572055
          ],
          [
            3.940739994470717,
            -0.1365479405500108,
            2.238377992942278
          ],
          [
            1.281837319037726,
            0.4356448336589309,
            1.845273182570088
          ],
          [
            6.523461004017735,
            1.824875640994127,
            2.144448195685043
          ],
          [
            7.77424605065629,
            0.05928126458020799,
            0.1940151449900602
          ],
          [
            12.9518656306912,
            1.46862065346904,
            0.3949909605179183
          ],
          [
            10.33353270839272,
            2.055795018835494,
            -0.1449580211997934
          ],
          [
            11.740250527079,
            0.4728637565345513,
            2.13994245533692
          ],
          [
            9.149821256936423,
            1.070783282731202,
            2.425331277386722
          ],
          [
            14.0709312071528,
            2.500851463221588,
            3.123344691316858
          ]
        ],
        "Stress": [
          [
            0,
            0,
            0
          ],
          [
            0,
            0,
            0
          ],
          [
            0,
            0,
            0
          ]
        ]
      }
    ],
    "EnergyStyle": "electronvolt",
    "ForcesStyle": "electronvoltperangstrom",
    "Label": "Cysani W 6154 gamma_surface 12",
    "LatticeStyle": "angstrom",
    "PositionsStyle": "angstrom",
    "StressStyle": "bar"
  }
}