{
  "Dataset": {
    "AtomTypeStyle": "chemicalsymbol",
    "Data": [
      {
        "AtomTypes": [
          "W",
          "W",
          "W",
          "W",
          "W",
          "W",
          "W",
          "W",
          "W",
          "W",
          "W",
          "W"
        ],
        "Charges": [
          0.014844326819600498,
          -0.031141007187935096,
          -0.031770923865227486,
          -0.0031441991325313794,
          0.00742978240321325,
          -0.009812164965461858,
          0.012865275990039825,
          -0.009710785143025709,
          -0.008400218142675494,
          0.025898552806336413,
          0.04049605530038946,
          -0.007554694882722586
        ],
        "Energy": -100.735,
        "Forces": [
          [
            -3.002225424914457,
            -2.24976098320998,
            0.3800615265981037
          ],
          [
            1.342351204631327,
            -1.928863976402246,
            1.119265471698863
          ],
          [
            0.6896669387687765,
            1.491967421860151,
            1.520740976721687
          ],
          [
            -2.953396212487465,
            2.61614541000645,
            0.09913348867667014
          ],
          [
            -0.0236700936235874,
            -2.800004041467052,
            -3.019923394097685
          ],
          [
            -0.4189419661002806,
            -3.386087944025159,
            2.792747485392792
          ],
          [
            0.154688311278347,
            3.311688766513361,
            3.328358483341
          ],
          [
            -0.2647691035230624,
            2.839844309002824,
            -2.489737831918532
          ],
          [
            2.047917794633917,
            -0.6095060122736436,
            -2.078716643122126
          ],
          [
            -0.3433581225925911,
            -2.486751248688432,
            -0.2188084801512959
          ],
          [
            0.3907033746393434,
            2.430713705560419,
            0.5021356220737391
          ],
          [
            2.381033299289733,
            0.7706145931233078,
            -1.935256705213214
          ]
        ],
        "Lattice": [
          [
            13.44857932906845,
            1.793143908542459,
            0.6339721089821562
          ],
          [
            0.0,
            4.48285977635615,
            0.0
          ],
          [
            0.0,
            0.0,
            3.169860554910782
          ]
        ],
        "NumAtoms": 12,
        "Positions": [
          [
            0.2597328100675597,
            -0.01287280099458248,
            -0.03074192237519226
          ],
          [
            2.289608376900456,
            2.256549284346235,
            -0.04339364335269359
          ],
          [
            2.298908427619,
            -0.1632060526096784,
            1.518914517354861
          ],
          [
            0.2808169916965725,
            1.974704402570245,
            1.547291889547362
          ],
          [
            4.437949252886258,
            0.1020491578845548,
            0.2131927264717648
          ],
          [
            6.656445934292459,
            2.403492225699387,
            -0.208338926096749
          ],
          [
            6.624275621806906,
            -0.1235135695429452,
            1.356407624799201
          ],
          [
            4.45289834404126,
            2.080583390750701,
            1.78805954814963
          ],
          [
            8.810339070707242,
            0.1247058696350647,
            0.1983290953233661
          ],
          [
            11.16509392264106,
            2.542719006456371,
            -0.05548477428688259
          ],
          [
            11.16001481224864,
            0.01711759132254453,
            1.469190953513103
          ],
          [
            8.806813140434818,
            2.246250843550553,
            1.756154585684578
          ]
        ],
        "Stress": [
          [
            0,
            0,
            0
          ],
          [
            0,
            0,
            0
          ],
          [
            0,
            0,
            0
          ]
        ]
      }
    ],
    "EnergyStyle": "electronvolt",
    "ForcesStyle": "electronvoltperangstrom",
    "Label": "Cysani W 7070 gamma_surface 12",
    "LatticeStyle": "angstrom",
    "PositionsStyle": "angstrom",
    "StressStyle": "bar"
  }
}