{
  "Dataset": {
    "AtomTypeStyle": "chemicalsymbol",
    "Data": [
      {
        "AtomTypes": [
          "W",
          "W",
          "W",
          "W",
          "W",
          "W",
          "W",
          "W",
          "W",
          "W",
          "W",
          "W"
        ],
        "Charges": [
          0.021008340264594944,
          -0.009073740909940477,
          -0.02860092633026356,
          -0.004125631751581407,
          0.004773162229239563,
          0.014898323339262191,
          0.02184042325204604,
          -0.007244686141256573,
          -0.002705932290905555,
          -0.039426976128400376,
          0.004480353370353617,
          0.024177291096851957
        ],
        "Energy": -103.035,
        "Forces": [
          [
            -1.770327226273572,
            1.782471189408506,
            -2.732858400482482
          ],
          [
            1.325671546742352,
            0.1889134608570225,
            -0.8044314419303564
          ],
          [
            1.139191838385479,
            -0.8400708852519284,
            2.379630856834353
          ],
          [
            -0.7435442110787037,
            0.1212151695244287,
            -1.991402575028753
          ],
          [
            -1.096730781718781,
            -0.1445319559164467,
            -1.619195470218625
          ],
          [
            1.798767974414972,
            0.09172639317007443,
            3.484940982299682
          ],
          [
            -0.7478074642600162,
            -0.2359949877849699,
            -1.371693618864014
          ],
          [
            2.292930985638116,
            -0.1536155594887297,
            3.565809927694627
          ],
          [
            -0.2709641381399003,
            0.4257667412073949,
            0.1706888270941725
          ],
          [
            -2.532264791275264,
            0.6282757865350882,
            -3.678635550193142
          ],
          [
            -1.891374231878717,
            -0.2935561470385636,
            -0.08203306106870967
          ],
          [
            2.496450499444034,
            -1.570599205221877,
            2.679179523863246
          ]
        ],
        "Lattice": [
          [
            15.63295833783864,
            0.5527085427035446,
            3.610277078938385
          ],
          [
            0.0,
            2.763542713517723,
            0.0
          ],
          [
            0.0,
            0.0,
            4.512846348672981
          ]
        ],
        "NumAtoms": 12,
        "Positions": [
          [
            0.1570535221343196,
            -0.3867013498774436,
            0.6233452181610981
          ],
          [
            5.114640115168965,
            0.8276713939478126,
            0.1510226816683631
          ],
          [
            2.598579590772289,
            1.706094561816825,
            0.2972010329624415
          ],
          [
            3.913766882386712,
            -0.1257686897171807,
            2.588116609963895
          ],
          [
            1.347717384127773,
            0.7071629746370525,
            2.808030956954988
          ],
          [
            6.443590757846775,
            1.806950079609156,
            2.085625781140288
          ],
          [
            7.873811788348971,
            0.05713080441405854,
            0.001889100145956224
          ],
          [
            12.97134950219657,
            1.161686189754571,
            -0.6420812196086843
          ],
          [
            10.4598113781493,
            1.906112687270689,
            -0.1500096515900933
          ],
          [
            11.74576696750521,
            0.1320745102043832,
            2.066045819627494
          ],
          [
            9.229698953107958,
            1.008781057940765,
            2.181821238572572
          ],
          [
            14.12548405136768,
            2.252976694070207,
            1.527531488020628
          ]
        ],
        "Stress": [
          [
            0,
            0,
            0
          ],
          [
            0,
            0,
            0
          ],
          [
            0,
            0,
            0
          ]
        ]
      }
    ],
    "EnergyStyle": "electronvolt",
    "ForcesStyle": "electronvoltperangstrom",
    "Label": "Cysani W 8533 gamma_surface 12",
    "LatticeStyle": "angstrom",
    "PositionsStyle": "angstrom",
    "StressStyle": "bar"
  }
}