{
  "Dataset": {
    "AtomTypeStyle": "chemicalsymbol",
    "Data": [
      {
        "AtomTypes": [
          "N",
          "N",
          "N",
          "N"
        ],
        "Charges": [
          1.2737577299155283e-06,
          1.2608519746560083e-06,
          -1.2651693498711605e-06,
          -1.269440355033816e-06
        ],
        "Energy": -19.46796944,
        "Forces": [
          [
            -0.217611,
            -0.0,
            0.726491
          ],
          [
            -0.217611,
            -0.0,
            -0.726491
          ],
          [
            0.217611,
            -0.726491,
            -0.0
          ],
          [
            0.217611,
            0.726491,
            -0.0
          ]
        ],
        "Lattice": [
          [
            20.0,
            0.0,
            0.0
          ],
          [
            0.0,
            20.0,
            0.0
          ],
          [
            0.0,
            0.0,
            20.0
          ]
        ],
        "NumAtoms": 4,
        "Positions": [
          [
            0.0,
            0.55625,
            1.1125
          ],
          [
            0.0,
            0.55625,
            0.0
          ],
          [
            2.875,
            0.0,
            0.55625
          ],
          [
            2.875,
            1.1125,
            0.55625
          ]
        ],
        "Stress": [
          [
            -152.5,
            0.0,
            0.0
          ],
          [
            0.0,
            -300.34,
            -0.0
          ],
          [
            0.0,
            -0.0,
            -300.3
          ]
        ]
      }
    ],
    "EnergyStyle": "electronvolt",
    "ForcesStyle": "electronvoltperangstrom",
    "Label": null,
    "LatticeStyle": "angstrom",
    "PositionsStyle": "angstrom",
    "StressStyle": "bar"
  }
}